{"ID-NB":{"name":"Mataram","x":465.3,"y":324.8},"ID-LA":{"name":"Bandar Lampung","x":228.5,"y":256.4},"ID-JI":{"name":"Sumenep","x":415.3,"y":290.4},"ID-KT":{"name":"Palangkaraya","x":416.6,"y":185.5},"ID-BA":{"name":"Denpasar","x":445.3,"y":326.4},"ID-RI":{"name":"Pekanbaru","x":143.8,"y":124.8},"ID-SA":{"name":"Manado","x":655.7,"y":104.8},"ID-YO":{"name":"Yogyakarta","x":339.4,"y":307.3},"ID-SG":{"name":"Kendari","x":606.4,"y":223.7},"ID-ST":{"name":"Palu","x":546.1,"y":157.0},"ID-KI":{"name":"Samarinda","x":487.4,"y":148.1},"ID-BE":{"name":"Bengkulu","x":162.3,"y":220.3},"ID-KB":{"name":"Pontianak","x":316.4,"y":137.8},"ID-JA":{"name":"Jambi","x":191.6,"y":172.0},"ID-PA":{"name":"Jayapura","x":1002.0,"y":192.6},"ID-AC":{"name":"Banda Aceh","x":10.5,"y":15.8},"ID-SB":{"name":"Padang","x":120.6,"y":158.1},"ID-JT":{"name":"Semarang","x":340.3,"y":289.5},"ID-SS":{"name":"Palembang","x":216.5,"y":202.3},"ID-KS":{"name":"Bandjarmasin","x":431.3,"y":210.0},"ID-SN":{"name":"Makassar","x":537.2,"y":249.5},"ID-SU":{"name":"Medan","x":83.2,"y":58.8},"ID-JB":{"name":"Bandung","x":278.1,"y":289.1}}